cryptoscan/__init__.py
cryptoscan/_version.py
cryptoscan/chain_parsers.py
cryptoscan/config.py
cryptoscan/exceptions.py
cryptoscan/factory.py
cryptoscan/metrics.py
cryptoscan/models.py
cryptoscan/networks.py
cryptoscan/rpc_client.py
cryptoscan/security.py
cryptoscan/universal_provider.py
cryptoscan/websocket_client.py
cryptoscan/adapters/__init__.py
cryptoscan/adapters/api_adapters.py
cryptoscan/adapters/base.py
cryptoscan/adapters/ton_adapter.py
cryptoscan/adapters/tron_adapter.py
cryptoscan/metrics/__init__.py
cryptoscan/metrics/collector.py
cryptoscan/metrics/global_metrics.py
cryptoscan/metrics/types.py
cryptoscan/monitoring/__init__.py
cryptoscan/monitoring/monitor.py
cryptoscan/monitoring/strategies.py
cryptoscan/parsers/__init__.py
cryptoscan/parsers/base.py
cryptoscan/parsers/bitcoin.py
cryptoscan/parsers/evm.py
cryptoscan/parsers/solana.py
cryptoscan/websocket/__init__.py
cryptoscan/websocket/client.py
cryptoscan/websocket/connection_manager.py
cryptoscan/websocket/message_processor.py
cryptoscan/websocket/subscription_manager.py
pycryptoscan-2.0.3.dist-info/licenses/LICENSE
tests/__init__.py
tests/conftest.py
tests/integration/__init__.py
tests/integration/test_monitors.py
tests/unit/__init__.py
tests/unit/test_metrics.py
tests/unit/test_models.py
tests/unit/test_parsers.py
tests/unit/test_security.py
pycryptoscan-2.0.3.dist-info/METADATA
pycryptoscan-2.0.3.dist-info/WHEEL
pycryptoscan-2.0.3.dist-info/top_level.txt
pycryptoscan-2.0.3.dist-info/RECORD
