Metadata-Version: 2.4
Name: pycryptoscan
Version: 2.0.3
Summary: Professional Real-Time Crypto Payment Monitoring Library for Python
Home-page: https://github.com/DedInc/cryptoscan
Author: DedInc.
Author-email: visitanimation@gmail.com
License: MIT
Project-URL: Bug Reports, https://github.com/DedInc/cryptoscan/issues
Project-URL: Source, https://github.com/DedInc/cryptoscan
Keywords: cryptocurrency,crypto,payment,monitoring,blockchain,solana,ethereum,bitcoin,async,httpx,http2,fintech
Classifier: Development Status :: 5 - Production/Stable
Classifier: Intended Audience :: Developers
Classifier: Operating System :: OS Independent
Classifier: Programming Language :: Python :: 3
Classifier: Programming Language :: Python :: 3.8
Classifier: Programming Language :: Python :: 3.9
Classifier: Programming Language :: Python :: 3.10
Classifier: Programming Language :: Python :: 3.11
Classifier: Programming Language :: Python :: 3.12
Classifier: Topic :: Software Development :: Libraries :: Python Modules
Classifier: Topic :: Internet :: WWW/HTTP
Classifier: Topic :: Office/Business :: Financial
Classifier: Topic :: Security :: Cryptography
Requires-Python: >=3.8
License-File: LICENSE
Requires-Dist: httpx[http2]<1.0.0,>=0.24.0
Dynamic: author
Dynamic: author-email
Dynamic: classifier
Dynamic: description
Dynamic: description-content-type
Dynamic: home-page
Dynamic: keywords
Dynamic: license
Dynamic: license-file
Dynamic: project-url
Dynamic: requires-dist
Dynamic: requires-python
Dynamic: summary
